chkp_harmony_endpoint_management_cli/__init__.py
chkp_harmony_endpoint_management_cli/index.py
chkp_harmony_endpoint_management_cli/logger.py
chkp_harmony_endpoint_management_cli/sdk_operations.py
chkp_harmony_endpoint_management_cli/generated/__init__.py
chkp_harmony_endpoint_management_cli/generated/build_info.py
chkp_harmony_endpoint_management_cli-1.0.22.data/data/requirements.txt
chkp_harmony_endpoint_management_cli-1.0.22.dist-info/LICENSE
chkp_harmony_endpoint_management_cli-1.0.22.dist-info/METADATA
chkp_harmony_endpoint_management_cli-1.0.22.dist-info/WHEEL
chkp_harmony_endpoint_management_cli-1.0.22.dist-info/entry_points.txt
chkp_harmony_endpoint_management_cli-1.0.22.dist-info/top_level.txt
chkp_harmony_endpoint_management_cli-1.0.22.dist-info/RECORD
