Metadata-Version: 2.2
Name: chkp-harmony-endpoint-management-cli
Version: 1.0.22
Summary: Harmony Endpoint Official CLI
Home-page: https://github.com/CheckPointSW/harmony-endpoint-management-cli
Author: Haim Kastner
Author-email: haimk@checkpoint.com
Maintainer: Haim Kastner
Maintainer-email: haimk@checkpoint.com
License: MIT
Keywords: harmony,endpoint,cli,checkpoint
Requires-Python: >=3.8,<4.0
License-File: LICENSE
Requires-Dist: chkp-harmony-endpoint-management-sdk<1.2.0,>=1.1.42
Dynamic: author
Dynamic: author-email
Dynamic: description
Dynamic: description-content-type
Dynamic: home-page
Dynamic: keywords
Dynamic: license
Dynamic: maintainer
Dynamic: maintainer-email
Dynamic: requires-dist
Dynamic: requires-python
Dynamic: summary
